CHANGELOG.md
LICENSE
README.md
bumpx/__about__.py
bumpx/__init__.py
bumpx/__main__.py
bumpx/config.py
bumpx/helpers.py
bumpx/hooks.py
bumpx/log.py
bumpx/releaser.py
bumpx/vcs.py
bumpx/version.py
bumpx-0.3.10.dist-info/LICENSE
bumpx-0.3.10.dist-info/METADATA
bumpx-0.3.10.dist-info/WHEEL
bumpx-0.3.10.dist-info/entry_points.txt
bumpx-0.3.10.dist-info/RECORD
