Metadata-Version: 2.1
Name: bumpx
Version: 0.3.10
Summary: Version bumper and Python package releaser
Home-page: https://github.com/datagouv/bumpx
License: LGPL
Keywords: version,bump,release,tag
Author: data.gouv.fr
Author-email: opendatateam@data.gouv.fr
Requires-Python: >=3.9,<4.0
Classifier: Development Status :: 4 - Beta
Classifier: Intended Audience :: Developers
Classifier: License :: OSI Approved :: GNU Library or Lesser General Public License (LGPL)
Classifier: License :: Other/Proprietary License
Classifier: Operating System :: OS Independent
Classifier: Programming Language :: Python :: 3
Classifier: Programming Language :: Python :: 3.9
Classifier: Programming Language :: Python :: 3.10
Classifier: Programming Language :: Python :: 3.11
Classifier: Programming Language :: Python :: 3.12
Classifier: Programming Language :: Python :: 3.13
Classifier: Topic :: Software Development :: Build Tools
Classifier: Topic :: Software Development :: Libraries :: Python Modules
Classifier: Topic :: System :: Software Distribution
Project-URL: Bug Tracker, https://github.com/datagouv/bumpx/issues
Project-URL: Documentation, https://bumpr.readthedocs.io/en/stable/
Project-URL: Repository, https://github.com/datagouv/bumpx
